pathdirector/__init__.py
pathdirector/application_dir.py
pathdirector/sys_dir.py
pathdirector-0.0.1.dist-info/LICENSE
pathdirector-0.0.1.dist-info/METADATA
pathdirector-0.0.1.dist-info/WHEEL
pathdirector-0.0.1.dist-info/top_level.txt
pathdirector-0.0.1.dist-info/RECORD
